feincms_mediaicons/__init__.py
feincms_mediaicons/models.py
feincms_mediaicons/tests.py
feincms_mediaicons/static/mediafile/dwg.png
feincms_mediaicons/static/mediafile/excel.png
feincms_mediaicons/static/mediafile/image.png
feincms_mediaicons/static/mediafile/pdf.png
feincms_mediaicons/static/mediafile/powerpoint.png
feincms_mediaicons/static/mediafile/text.png
feincms_mediaicons/static/mediafile/word.png
feincms_mediaicons/static/mediafile/zip.png
feincms_mediaicons/templates/content/mediafile/default.html
feincms_mediaicons/templates/content/mediafile/doc.html
feincms_mediaicons/templates/content/mediafile/docx.html
feincms_mediaicons/templates/content/mediafile/dwg.html
feincms_mediaicons/templates/content/mediafile/dwg.html~
feincms_mediaicons/templates/content/mediafile/filelink.html
feincms_mediaicons/templates/content/mediafile/image.html
feincms_mediaicons/templates/content/mediafile/image_default.html
feincms_mediaicons/templates/content/mediafile/image_pic_wide.html
feincms_mediaicons/templates/content/mediafile/mp3.html
feincms_mediaicons/templates/content/mediafile/pdf.html
feincms_mediaicons/templates/content/mediafile/ppt.html
feincms_mediaicons/templates/content/mediafile/pptx.html
feincms_mediaicons/templates/content/mediafile/rtf.html
feincms_mediaicons/templates/content/mediafile/txt.html
feincms_mediaicons/templates/content/mediafile/xls.html
feincms_mediaicons/templates/content/mediafile/xlsx.html
feincms_mediaicons/templates/content/mediafile/zip.html
feincms_mediaicons-1.0.3.dist-info/DESCRIPTION.rst
feincms_mediaicons-1.0.3.dist-info/METADATA
feincms_mediaicons-1.0.3.dist-info/RECORD
feincms_mediaicons-1.0.3.dist-info/WHEEL
feincms_mediaicons-1.0.3.dist-info/metadata.json
feincms_mediaicons-1.0.3.dist-info/top_level.txt
